superblocks_agent_sdk/__init__.py
superblocks_agent_sdk/_constant.py
superblocks_agent_sdk/_version.py
superblocks_agent_sdk/_decorator/__init__.py
superblocks_agent_sdk/_util/__init__.py
superblocks_agent_sdk/_util/convert.py
superblocks_agent_sdk/_util/decorator.py
superblocks_agent_sdk/_util/doc.py
superblocks_agent_sdk/_util/generate.py
superblocks_agent_sdk/api/Api.py
superblocks_agent_sdk/api/Config.py
superblocks_agent_sdk/api/Result.py
superblocks_agent_sdk/api/ViewMode.py
superblocks_agent_sdk/api/__init__.py
superblocks_agent_sdk/client/Client.py
superblocks_agent_sdk/client/Config.py
superblocks_agent_sdk/client/__init__.py
superblocks_agent_sdk/testing/__init__.py
superblocks_agent_sdk/testing/step/Mock.py
superblocks_agent_sdk/testing/step/Params.py
superblocks_agent_sdk/testing/step/__init__.py
superblocks_agent_sdk/types_/_BaseEnum.py
superblocks_agent_sdk/types_/_DictDeserializable.py
superblocks_agent_sdk/types_/_DictSerializable.py
superblocks_agent_sdk/types_/_Dictizable.py
superblocks_agent_sdk/types_/__init__.py
superblocks_agent_sdk/types_/_client.py
superblocks_agent_sdk/types_/common.py
superblocks_types/__init__.py
superblocks_types/api/__init__.py
superblocks_types/api/v1/__init__.py
superblocks_types/api/v1/api_pb2.py
superblocks_types/api/v1/api_pb2_grpc.py
superblocks_types/api/v1/blocks_pb2.py
superblocks_types/api/v1/blocks_pb2_grpc.py
superblocks_types/api/v1/event_pb2.py
superblocks_types/api/v1/event_pb2_grpc.py
superblocks_types/api/v1/service_pb2.py
superblocks_types/api/v1/service_pb2_grpc.py
superblocks_types/buf/__init__.py
superblocks_types/buf/validate/__init__.py
superblocks_types/buf/validate/expression_pb2.py
superblocks_types/buf/validate/expression_pb2_grpc.py
superblocks_types/buf/validate/validate_pb2.py
superblocks_types/buf/validate/validate_pb2_grpc.py
superblocks_types/buf/validate/priv/__init__.py
superblocks_types/buf/validate/priv/private_pb2.py
superblocks_types/buf/validate/priv/private_pb2_grpc.py
superblocks_agent_sdk-0.1.1.dist-info/LICENSE
superblocks_agent_sdk-0.1.1.dist-info/METADATA
superblocks_agent_sdk-0.1.1.dist-info/WHEEL
superblocks_agent_sdk-0.1.1.dist-info/top_level.txt
superblocks_agent_sdk-0.1.1.dist-info/RECORD
