Metadata-Version: 2.1
Name: superblocks-agent-sdk
Version: 0.1.1
Summary: The Official Python SDK for Superblocks
Home-page: https://github.com/superblocksteam/orchestrator/tree/main/clients/python
Author: Joey Greco
Author-email: joeyagreco@gmail.com
License: MIT
Keywords: superblocks api sdk
Requires-Python: >=3.10
License-File: LICENSE
Requires-Dist: protobuf ~=5.27.0
Requires-Dist: grpcio ~=1.64.1
